NewtApi/__init__.py
NewtApi/client.py
NewtApi/network.py
NewtApi-1.0.0.dist-info/LICENCE
NewtApi-1.0.0.dist-info/METADATA
NewtApi-1.0.0.dist-info/WHEEL
NewtApi-1.0.0.dist-info/top_level.txt
NewtApi-1.0.0.dist-info/RECORD
