Metadata-Version: 2.1
Name: NewtApi
Version: 1.0.0
Summary: Python library for working with server Api (New Api)
Home-page: https://www.arver.ir/
Author: AbolfazlMirzaei
Author-email: newtapi@gmail.com
License: MIT
Keywords: api,API,Api,newtapi,NewtApi,NewtAPI,NEWTAPI
Classifier: Development Status :: 3 - Alpha
Classifier: Intended Audience :: Developers
Classifier: Topic :: Software Development :: Build Tools
Classifier: License :: OSI Approved :: MIT License
Classifier: Programming Language :: Python :: Implementation :: PyPy
Classifier: Programming Language :: Python :: 3
Classifier: Programming Language :: Python :: 3.4
Classifier: Programming Language :: Python :: 3.5
Classifier: Programming Language :: Python :: 3.6
Classifier: Programming Language :: Python :: 3.7
Classifier: Programming Language :: Python :: 3.8
Classifier: Programming Language :: Python :: 3.9
Classifier: Programming Language :: Python :: 3.10
Classifier: Programming Language :: Python :: 3.11
License-File: LICENCE
Requires-Dist: requests ==2.31.0
Requires-Dist: urllib3 ==2.2.0
